csv_to_sql_dump/__init__.py
csv_to_sql_dump-0.0.8.dist-info/METADATA
csv_to_sql_dump-0.0.8.dist-info/WHEEL
csv_to_sql_dump-0.0.8.dist-info/licenses/LICENSE
csv_to_sql_dump-0.0.8.dist-info/RECORD
