Metadata-Version: 2.4
Name: csv_to_sql_dump
Version: 0.0.8
Summary: From .csv file, create .sql dump containing CREATE and INSERT statements.
Project-URL: Homepage, https://github.com/zlliu246/csv_to_sql_dump
Project-URL: Issues, https://github.com/zlliu246/csv_to_sql_dump/issues
Author-email: Liu Zuo Lin <zlliu246@gmail.com>
License-File: LICENSE
Classifier: License :: OSI Approved :: MIT License
Classifier: Operating System :: OS Independent
Classifier: Programming Language :: Python :: 3
Requires-Python: >=3.8
Requires-Dist: pandas
